filez/__init__.py
filez/setup.py
filez_MagmaMc-1.0.2.dist-info/METADATA
filez_MagmaMc-1.0.2.dist-info/WHEEL
filez_MagmaMc-1.0.2.dist-info/top_level.txt
filez_MagmaMc-1.0.2.dist-info/RECORD
