Metadata-Version: 2.1
Name: filez-MagmaMc
Version: 1.0.2
Summary: read, write, scan in json
Author: MagmaMc
Author-email: kaicycle11@gmail.com
License: UNKNOWN
Platform: UNKNOWN
Classifier: Programming Language :: Python :: 3
Classifier: License :: OSI Approved :: MIT License
Classifier: Operating System :: OS Independent
Requires-Python: >=3.6
